hdf5objects/__init__.py
hdf5objects/arrays/__init__.py
hdf5objects/arrays/hdf5eegcontainer.py
hdf5objects/dataset/__init__.py
hdf5objects/dataset/axes/__init__.py
hdf5objects/dataset/axes/axiscomponent.py
hdf5objects/dataset/axes/channelaxiscomponent.py
hdf5objects/dataset/axes/coordinateaxiscomponent.py
hdf5objects/dataset/axes/idaxiscomponent.py
hdf5objects/dataset/axes/labelaxiscomponent.py
hdf5objects/dataset/axes/regionreferenceaxiscomponent.py
hdf5objects/dataset/axes/sampleaxiscomponent.py
hdf5objects/dataset/axes/timeaxiscomponent.py
hdf5objects/dataset/basedatasetcomponent.py
hdf5objects/dataset/components/__init__.py
hdf5objects/dataset/components/geometrycomponent.py
hdf5objects/dataset/components/idcomponent.py
hdf5objects/dataset/components/objectreferencecomponent.py
hdf5objects/dataset/components/regionreferencecomponent.py
hdf5objects/dataset/components/shapescomponent.py
hdf5objects/dataset/components/timeseriescomponent.py
hdf5objects/dataset/maps/__init__.py
hdf5objects/dataset/maps/basetimeseriesmap.py
hdf5objects/dataset/maps/electricalseriesmap.py
hdf5objects/dataset/maps/shapesmap.py
hdf5objects/fileobjects/__init__.py
hdf5objects/fileobjects/basehdf5.py
hdf5objects/fileobjects/hdf5eeg.py
hdf5objects/groups/__init__.py
hdf5objects/groups/linkedgroup.py
hdf5objects/hdf5bases/__init__.py
hdf5objects/hdf5bases/hdf5attributes.py
hdf5objects/hdf5bases/hdf5basecomponent.py
hdf5objects/hdf5bases/hdf5baseobject.py
hdf5objects/hdf5bases/hdf5caster.py
hdf5objects/hdf5bases/hdf5dataset.py
hdf5objects/hdf5bases/hdf5file.py
hdf5objects/hdf5bases/hdf5group.py
hdf5objects/hdf5bases/hdf5map.py
hdf5objects/header.py
hdf5objects/py.typed
hdf5objects/treehierarchy/__init__.py
hdf5objects/treehierarchy/datasetcomponents/__init__.py
hdf5objects/treehierarchy/datasetcomponents/nodedatasetcomponent.py
hdf5objects/treehierarchy/generalcomponents/__init__.py
hdf5objects/treehierarchy/generalcomponents/rootnodecomponent.py
hdf5objects-0.5.0.dist-info/LICENSE.rst
hdf5objects-0.5.0.dist-info/METADATA
hdf5objects-0.5.0.dist-info/WHEEL
hdf5objects-0.5.0.dist-info/entry_points.txt
hdf5objects-0.5.0.dist-info/RECORD
