Metadata-Version: 2.1
Name: hdf5objects
Version: 0.5.0
Summary: hdf5objects
Home-page: https://github.com/FongAnthonyM/hdf5objects
License: MIT
Author: Anthony Fong
Author-email: FongAnthonyM@gmail.com
Requires-Python: >=3.10,<4.0
Classifier: Development Status :: 3 - Alpha
Classifier: License :: OSI Approved :: MIT License
Classifier: Programming Language :: Python :: 3
Classifier: Programming Language :: Python :: 3.10
Classifier: Programming Language :: Python :: 3.11
Requires-Dist: baseobjects (>=1.11.0)
Requires-Dist: bidict (>=0.22.0)
Requires-Dist: classversioning (>=0.7.0)
Requires-Dist: dspobjects (>=0.4.0)
Requires-Dist: h5py (>=3.5.0)
Requires-Dist: numpy (>=1.25.1)
Requires-Dist: proxyarrays (>=0.6.0)
Project-URL: Changelog, https://github.com/FongAnthonyM/hdf5objects/releases
Project-URL: Documentation, https://hdf5objects.readthedocs.io
Project-URL: Repository, https://github.com/FongAnthonyM/hdf5objects
